Metadata-Version: 2.1
Name: tlingua
Version: 0.0.1
Summary: A little library for text/grammar processing.
Home-page: https://github.com/LudwigVonChesterfield/TLingua
Author: Luduk
Author-email: ningawent@gmail.com
License: MIT
Download-URL: https://github.com/LudwigVonChesterfield/TLingua/archive/v_000.000.001.tar.gz
Keywords: TAGS,STRINGS,GRAMMAR,LANGUAGE
Platform: UNKNOWN
Classifier: Development Status :: 3 - Alpha
Classifier: Intended Audience :: Developers
Classifier: Topic :: Software Development :: Build Tools
Classifier: License :: OSI Approved :: MIT License
Classifier: Programming Language :: Python :: 3.6
